{"id":"id-1224","birthDate":"Nov 28, 1984 12:00:00 AM","gender":"F","age":29,"length":416,"events":[{"date":"Jun 26, 2014 12:00:00 AM","system":"http://hl7.org/fhir/sid/icd-9-cm","icdCode":"V72.31"},{"date":"Oct 30, 2013 12:00:00 AM","system":"http://hl7.org/fhir/sid/icd-9-cm","icdCode":"692.9"},{"date":"Jul 22, 2013 12:00:00 AM","system":"http://hl7.org/fhir/sid/icd-9-cm","icdCode":"455.0"},{"date":"Jul 22, 2013 12:00:00 AM","system":"http://hl7.org/fhir/sid/icd-9-cm","icdCode":"569.3"},{"date":"Jul 22, 2013 12:00:00 AM","system":"http://hl7.org/fhir/sid/icd-9-cm","icdCode":"787.99"},{"date":"Jul 12, 2013 12:00:00 AM","system":"http://hl7.org/fhir/sid/icd-9-cm","icdCode":"465.9"},{"date":"May 31, 2013 12:00:00 AM","system":"http://hl7.org/fhir/sid/icd-9-cm","icdCode":"789.00"},{"date":"May 10, 2013 12:00:00 AM","system":"http://hl7.org/fhir/sid/icd-9-cm","icdCode":"789.01"},{"date":"May 6, 2013 12:00:00 AM","system":"http://hl7.org/fhir/sid/icd-9-cm","icdCode":"569.3"}]}